CHANGES.rst
MANIFEST.in
README.rst
setup.py
atreal/__init__.py
atreal.usersinout.egg-info/PKG-INFO
atreal.usersinout.egg-info/SOURCES.txt
atreal.usersinout.egg-info/dependency_links.txt
atreal.usersinout.egg-info/entry_points.txt
atreal.usersinout.egg-info/namespace_packages.txt
atreal.usersinout.egg-info/not-zip-safe
atreal.usersinout.egg-info/requires.txt
atreal.usersinout.egg-info/top_level.txt
atreal/usersinout/__init__.py
atreal/usersinout/config.py
atreal/usersinout/configure.zcml
atreal/usersinout/interfaces.py
atreal/usersinout/browser/__init__.py
atreal/usersinout/browser/configure.zcml
atreal/usersinout/browser/usersinout.pt
atreal/usersinout/browser/usersinout.py
atreal/usersinout/browser/usersinout_icon.png
atreal/usersinout/locales/atreal.usersinout.pot
atreal/usersinout/locales/de/LC_MESSAGES/atreal.usersinout.po
atreal/usersinout/locales/fr/LC_MESSAGES/atreal.usersinout.po
atreal/usersinout/profiles/default/actionicons.xml
atreal/usersinout/profiles/default/browserlayer.xml
atreal/usersinout/profiles/default/controlpanel.xml
atreal/usersinout/profiles/default/metadata.xml
atreal/usersinout/profiles/uninstall/actionicons.xml
atreal/usersinout/profiles/uninstall/browserlayer.xml
atreal/usersinout/profiles/uninstall/controlpanel.xml
docs/INSTALL.txt
docs/LICENSE.GPL
docs/LICENSE.txt