Metadata-Version: 1.1
Name: atreal.usersinout
Version: 1.2.3
Summary: Import / export users via CSV files
Home-page: http://www.atreal.net
Author: atReal
Author-email: contact@atreal.net
License: GPL
Keywords: zope plone atreal users import export csv
Platform: UNKNOWN
Classifier: Framework :: Plone
Classifier: Programming Language :: Python
Classifier: Topic :: Software Development :: Libraries :: Python Modules
